filterablelist.py
filterablelist-0.1.1.dist-info/LICENSE.txt
filterablelist-0.1.1.dist-info/METADATA
filterablelist-0.1.1.dist-info/WHEEL
filterablelist-0.1.1.dist-info/top_level.txt
filterablelist-0.1.1.dist-info/RECORD
