Metadata-Version: 2.1
Name: filterablelist
Version: 0.1.1
Summary: A list with built in filtering syntax.
Home-page: https://github.com/fridrik-juliusson/filterablelist
Author: Fridrik Juliusson
Project-URL: Documentation, https://github.com/fridrik-juliusson/filterablelist/
Project-URL: Bug Reports, https://github.com/fridrik-juliusson/filterablelist/issues
Project-URL: Say Thanks!, https://fridrikjuliusson.com/
Project-URL: Source, https://github.com/fridrik-juliusson/filterablelist/
Keywords: list,filter,development,utility
Classifier: Intended Audience :: Developers
Classifier: Intended Audience :: Science/Research
Classifier: Topic :: Utilities
Classifier: License :: OSI Approved :: MIT License
Classifier: Programming Language :: Python :: 3
Classifier: Programming Language :: Python :: 3.6
Classifier: Programming Language :: Python :: 3.7
Classifier: Programming Language :: Python :: 3.8
Classifier: Programming Language :: Python :: 3.9
Classifier: Programming Language :: Python :: 3.10
Classifier: Programming Language :: Python :: 3 :: Only
Requires-Python: >=3.6, <4
License-File: LICENSE.txt
